dam_lev/__init__.py
dam_lev/algorithm.py
dam_lev-0.1.2.dist-info/LICENSE
dam_lev-0.1.2.dist-info/METADATA
dam_lev-0.1.2.dist-info/WHEEL
dam_lev-0.1.2.dist-info/top_level.txt
dam_lev-0.1.2.dist-info/RECORD
