Metadata-Version: 2.1
Name: dam-lev
Version: 0.1.2
Summary: Implements the Damerau–Levenshtein diff algorithm
Home-page: https://github.com/nickeldan/dam_lev
Author: Daniel Walker
Keywords: diff
Classifier: Programming Language :: Python :: 3
Classifier: License :: OSI Approved :: MIT License
Requires-Python: >=3.8
License-File: LICENSE
Provides-Extra: test
Requires-Dist: tox ; extra == 'test'
Requires-Dist: pytest ; extra == 'test'
Requires-Dist: black ; extra == 'test'
Requires-Dist: mypy ; extra == 'test'
